imgvid_utils/__init__.py
imgvid_utils/__main__.py
imgvid_utils/arg_parser.py
imgvid_utils/file_ops.py
imgvid_utils/image.py
imgvid_utils/make_random_vid.py
imgvid_utils/video.py
imgvid_utils-0.2.1.dist-info/LICENSE
imgvid_utils-0.2.1.dist-info/METADATA
imgvid_utils-0.2.1.dist-info/WHEEL
imgvid_utils-0.2.1.dist-info/top_level.txt
imgvid_utils-0.2.1.dist-info/RECORD
