Metadata-Version: 2.1
Name: imgvid-utils
Version: 0.2.1
Summary: A package that provides helpful utilities to interact with videos and images through OpenCV.
Home-page: https://github.com/philippeitis/imgvid_utils
Author: Philippe Solodov
Author-email: solop1906@gmail.com
Classifier: Programming Language :: Python :: 3
Classifier: License :: OSI Approved :: MIT License
Classifier: Operating System :: OS Independent
Requires-Python: >=3.6
License-File: LICENSE
Requires-Dist: opencv-python (==4.6.0.66)
